multiple_minimum_monte_carlo/__init__.py
multiple_minimum_monte_carlo/calculation.py
multiple_minimum_monte_carlo/cheminformatics.py
multiple_minimum_monte_carlo/conformer.py
multiple_minimum_monte_carlo/conformer_ensemble.py
multiple_minimum_monte_carlo/multiproc.py
multiple_minimum_monte_carlo-1.0.0.dist-info/licenses/LICENSE
multiple_minimum_monte_carlo-1.0.0.dist-info/METADATA
multiple_minimum_monte_carlo-1.0.0.dist-info/WHEEL
multiple_minimum_monte_carlo-1.0.0.dist-info/top_level.txt
multiple_minimum_monte_carlo-1.0.0.dist-info/RECORD
