Metadata-Version: 2.4
Name: multiple-minimum-monte-carlo
Version: 1.0.0
Summary: Open source implementation of multiple minimum Monte Carlo
Author: Nicholas Casetti
License: MIT License
Requires-Python: >=3.8
License-File: LICENSE
Requires-Dist: ase
Requires-Dist: rdkit
Requires-Dist: scipy
Requires-Dist: torch
Dynamic: license-file
